[
    {
        "id": 2,
        "name": "Haled Husein",
        "username": "Haled",
        "email": "haledhusein@gmail.com",
        "phone": "32112313",
        "website": "FMorb.af"
    },
    {
        "id": 3,
        "name": "Anna Samdy",
        "username": "annakssh",
        "email": "annnna@yahoo.com",
        "phone": "32112313",
        "website": "WhoKilledChaik.ge"
    },
    {
        "id": 4,
        "name": "Dato Turiashvili",
        "username": "Turisha",
        "email": "DTDT@gmail.jp",
        "phone": "32112313",
        "website": "jeans.ussr"
    },
    {
        "id": 5,
        "name": "Naoko",
        "username": "naokogirl",
        "email": "naok22@jmail.jp",
        "phone": "32112313",
        "website": "NWood.jp"
    },
    {
        "id": 6,
        "name": "Elon Musk",
        "username": "Ilo",
        "email": "ilona@tesla.com",
        "phone": "1-111-111-11",
        "website": "tesla.com"
    },
    {
        "name": "some one",
        "username": "someone",
        "email": "smn@gmail.com",
        "phone": "123456789",
        "website": "apple.com",
        "id": 1470695,
        "extension": "jpg"
    }
]